streamlit_voice_pipeline/__init__.py
streamlit_voice_pipeline/audio_capture_streaming.py
streamlit_voice_pipeline/audio_player_streaming.py
streamlit_voice_pipeline/pipeline.py
streamlit_voice_pipeline-1.0.0.dist-info/licenses/LICENSE
streamlit_voice_pipeline-1.0.0.dist-info/METADATA
streamlit_voice_pipeline-1.0.0.dist-info/WHEEL
streamlit_voice_pipeline-1.0.0.dist-info/top_level.txt
streamlit_voice_pipeline-1.0.0.dist-info/RECORD
