Metadata-Version: 2.4
Name: streamlit-voice-pipeline
Version: 1.0.0
Summary: A Streamlit-ready voice pipeline for real-time conversation with OpenAI's GPT-4o Realtime API
Home-page: https://github.com/yourusername/streamlit-voice-pipeline
Author: Your Name
Author-email: Your Name <your.email@example.com>
Maintainer-email: Your Name <your.email@example.com>
License: MIT
Project-URL: Homepage, https://github.com/yourusername/streamlit-voice-pipeline
Project-URL: Documentation, https://github.com/yourusername/streamlit-voice-pipeline/blob/main/README.md
Project-URL: Repository, https://github.com/yourusername/streamlit-voice-pipeline.git
Project-URL: Bug Tracker, https://github.com/yourusername/streamlit-voice-pipeline/issues
Keywords: streamlit,voice,openai,realtime,audio,speech,gpt-4o,conversation,ai
Classifier: Development Status :: 4 - Beta
Classifier: Intended Audience :: Developers
Classifier: License :: OSI Approved :: MIT License
Classifier: Operating System :: OS Independent
Classifier: Programming Language :: Python :: 3
Classifier: Programming Language :: Python :: 3.8
Classifier: Programming Language :: Python :: 3.9
Classifier: Programming Language :: Python :: 3.10
Classifier: Programming Language :: Python :: 3.11
Classifier: Topic :: Software Development :: Libraries :: Python Modules
Classifier: Topic :: Multimedia :: Sound/Audio
Classifier: Topic :: Scientific/Engineering :: Artificial Intelligence
Classifier: Topic :: Internet :: WWW/HTTP :: Dynamic Content
Classifier: Topic :: Software Development :: User Interfaces
Requires-Python: >=3.8
License-File: LICENSE
Requires-Dist: streamlit>=1.25.0
Requires-Dist: websockets>=11.0
Requires-Dist: numpy>=1.21.0
Requires-Dist: asyncio-mqtt>=0.11.0
Requires-Dist: pyaudio>=0.2.11
Provides-Extra: dev
Requires-Dist: pytest>=6.0; extra == "dev"
Requires-Dist: pytest-asyncio>=0.18.0; extra == "dev"
Requires-Dist: black>=22.0; extra == "dev"
Requires-Dist: flake8>=4.0; extra == "dev"
Requires-Dist: mypy>=0.950; extra == "dev"
Dynamic: author
Dynamic: home-page
Dynamic: license-file
Dynamic: requires-python
